Xingguangti/Dockerfile
Xingguangti/README.md
Xingguangti/__init__.py
Xingguangti/__main__.py
Xingguangti/file.epub
Xingguangti/index.html
Xingguangti/css/__init__.py
Xingguangti/css/annotations.css
Xingguangti/css/main.css
Xingguangti/css/normalize.css
Xingguangti/css/popup.css
Xingguangti/font/__init__.py
Xingguangti/font/fontello.eot
Xingguangti/font/fontello.svg
Xingguangti/font/fontello.ttf
Xingguangti/font/fontello.woff
Xingguangti/img/__init__.py
Xingguangti/img/annotator-glyph-sprite.png
Xingguangti/img/annotator-icon-sprite.png
Xingguangti/img/apple-touch-icon.png
Xingguangti/img/cancelfullscreen.png
Xingguangti/img/close.png
Xingguangti/img/fullscreen.png
Xingguangti/img/loader.gif
Xingguangti/img/menu-icon.png
Xingguangti/img/save.png
Xingguangti/img/saved.png
Xingguangti/img/settings-s.png
Xingguangti/img/settings.png
Xingguangti/img/star.png
Xingguangti/js/__init__.py
Xingguangti/js/epub.js
Xingguangti/js/epub.min.js
Xingguangti/js/epub.min.map
Xingguangti/js/hooks.min.js
Xingguangti/js/hooks.min.map
Xingguangti/js/reader.js
Xingguangti/js/reader.js.map
Xingguangti/js/reader.min.js
Xingguangti/js/reader.min.map
Xingguangti/js/hooks/__init__.py
Xingguangti/js/hooks/extensions/__init__.py
Xingguangti/js/hooks/extensions/highlight.js
Xingguangti/js/libs/__init__.py
Xingguangti/js/libs/jquery.min.js
Xingguangti/js/libs/localforage.min.js
Xingguangti/js/libs/screenfull.js
Xingguangti/js/libs/screenfull.min.js
Xingguangti/js/libs/zip.min.js
Xingguangti/js/plugins/__init__.py
Xingguangti/js/plugins/hypothesis.js
Xingguangti/js/plugins/search.js
xingguangti-2022.10.7.1.dist-info/METADATA
xingguangti-2022.10.7.1.dist-info/WHEEL
xingguangti-2022.10.7.1.dist-info/entry_points.txt
xingguangti-2022.10.7.1.dist-info/top_level.txt
xingguangti-2022.10.7.1.dist-info/RECORD
